ar_site_maker/__init__.py
ar_site_maker/core.py
ar_site_maker/error.py
ar_site_maker/template.py
ar_site_maker/utlis.py
ar_site_maker-1.0.1.dist-info/METADATA
ar_site_maker-1.0.1.dist-info/WHEEL
ar_site_maker-1.0.1.dist-info/entry_points.txt
ar_site_maker-1.0.1.dist-info/top_level.txt
ar_site_maker-1.0.1.dist-info/RECORD
