Metadata-Version: 2.1
Name: ar-site-maker
Version: 1.0.1
Summary: A tool to create a website where 3D models can be viewed using AR technology.
Home-page: https://github.com/enfy-space/ArSiteMaker
Author: Taiyu Honma(ENFY)
Author-email: enfy.t.honma@gmail.com
Classifier: Programming Language :: Python :: 3.7
Classifier: License :: OSI Approved :: MIT License
Classifier: Operating System :: OS Independent
Requires-Dist: qrcode
Requires-Dist: pymarker
Requires-Dist: Pillow
Requires-Dist: fire
